{
    "name": "whhg-icons",
    "description": "Glyph Icon Font from WebHostingHub. 2075 High quality icons that are easy to use with Bootstrap, other CSS frameworks and in any web projects. They also work in desktop software such as Adobe Photoshop or Microsoft Word. They are perfect for use in mobile developement on Android or iOS devices.. http://http://www.webhostinghub.com/glyphs ",
    "homepage": "https://github.com/praneybehl/Meteor-WebHostingHub-Glyph-Icons",
    "author": "Praney Behl (http://fishnjavascript.com)",
    "version": "0.1.0",
    "git": "https://github.com/praneybehl/Meteor-WebHostingHub-Glyph-Icons.git",
    "packages": {
    }
}